tartrl/__init__.py
tartrl/algorithms/__init__.py
tartrl/algorithms/base_algorithm.py
tartrl/algorithms/ppo.py
tartrl/buffers/__init__.py
tartrl/buffers/normal_buffer.py
tartrl/buffers/replay_data.py
tartrl/buffers/utils/__init__.py
tartrl/buffers/utils/obs_data.py
tartrl/buffers/utils/util.py
tartrl/cli/__init__.py
tartrl/cli/cli.py
tartrl/cli/train.py
tartrl/configs/__init__.py
tartrl/configs/config.py
tartrl/datasets/__init__.py
tartrl/drivers/__init__.py
tartrl/drivers/base_driver.py
tartrl/drivers/onpolicy_driver.py
tartrl/drivers/rl_driver.py
tartrl/envs/__init__.py
tartrl/envs/common/__init__.py
tartrl/envs/common/registration.py
tartrl/envs/wrappers/__init__.py
tartrl/envs/wrappers/tartrl_wrapper.py
tartrl/envs/wrappers/venv.py
tartrl/modules/__init__.py
tartrl/modules/base_module.py
tartrl/modules/model_config.py
tartrl/modules/ppo_module.py
tartrl/modules/rl_module.py
tartrl/modules/common/__init__.py
tartrl/modules/common/base_net.py
tartrl/modules/common/ppo_net.py
tartrl/modules/networks/__init__.py
tartrl/modules/networks/base_policy_network.py
tartrl/modules/networks/base_value_network.py
tartrl/modules/networks/policy_network.py
tartrl/modules/networks/policy_value_network.py
tartrl/modules/networks/value_network.py
tartrl/modules/networks/utils/FcEncoder.py
tartrl/modules/networks/utils/__init__.py
tartrl/modules/networks/utils/act.py
tartrl/modules/networks/utils/attention.py
tartrl/modules/networks/utils/cnn.py
tartrl/modules/networks/utils/distributed_utils.py
tartrl/modules/networks/utils/distributions.py
tartrl/modules/networks/utils/mix.py
tartrl/modules/networks/utils/mlp.py
tartrl/modules/networks/utils/popart.py
tartrl/modules/networks/utils/pre_model_util.py
tartrl/modules/networks/utils/rnn.py
tartrl/modules/networks/utils/transformer_act.py
tartrl/modules/networks/utils/util.py
tartrl/modules/networks/utils/utils.py
tartrl/modules/utils/__init__.py
tartrl/modules/utils/util.py
tartrl/modules/utils/valuenorm.py
tartrl/runners/__init__.py
tartrl-0.0.3.dist-info/LICENSE.txt
tartrl-0.0.3.dist-info/METADATA
tartrl-0.0.3.dist-info/WHEEL
tartrl-0.0.3.dist-info/entry_points.txt
tartrl-0.0.3.dist-info/top_level.txt
tartrl-0.0.3.dist-info/RECORD
